hgx/__init__.py
hgx/accounting.py
hgx/app.py
hgx/bootstrapping.py
hgx/comms.py
hgx/config.py
hgx/core.py
hgx/daemon.py
hgx/dispatch.py
hgx/embed.py
hgx/exceptions.py
hgx/gao.py
hgx/hypothetical.py
hgx/inquisition.py
hgx/ipc.py
hgx/lawyer.py
hgx/librarian.py
hgx/logutils.py
hgx/objproxy.py
hgx/persistence.py
hgx/postal.py
hgx/privateer.py
hgx/remotes.py
hgx/rolodex.py
hgx/service.py
hgx/undertaker.py
hgx/utils.py
hgx-0.1.0.dist-info/DESCRIPTION.rst
hgx-0.1.0.dist-info/METADATA
hgx-0.1.0.dist-info/RECORD
hgx-0.1.0.dist-info/WHEEL
hgx-0.1.0.dist-info/metadata.json
hgx-0.1.0.dist-info/top_level.txt
